dask_elk/__init__.py
dask_elk/client.py
dask_elk/delayed_methods.py
dask_elk/helpers.py
dask_elk/parsers.py
dask_elk/reader.py
dask_elk/elk_entities/__init__.py
dask_elk/elk_entities/index.py
dask_elk/elk_entities/node.py
dask_elk/elk_entities/shards.py
dask_elk-0.4.0.dist-info/LICENSE
dask_elk-0.4.0.dist-info/METADATA
dask_elk-0.4.0.dist-info/WHEEL
dask_elk-0.4.0.dist-info/top_level.txt
dask_elk-0.4.0.dist-info/RECORD
