Metadata-Version: 2.1
Name: dask-elk
Version: 0.4.0
Summary: Dask connection with Elasticsearch
Home-page: https://github.com/avlahop/dask-elk
Maintainer: Apostolos Vlachopoulos
Maintainer-email: avlahop@gmail.com
License: GPLv3
Project-URL: Documentation, https://dask-elk.readthedocs.io
Keywords: elasticsearch dask parallel
Platform: UNKNOWN
Classifier: Programming Language :: Python :: 3
Classifier: Programming Language :: Python :: 3.6
Classifier: Development Status :: 4 - Beta
Classifier: License :: OSI Approved :: GNU General Public License (GPL)
Requires-Python: >=2.7
Requires-Dist: dask[complete]
Requires-Dist: elasticsearch (>=6.2)
Requires-Dist: pandas (>=0.19.0)
